colorlabels.py
colorlabels-0.7.0.dist-info/LICENSE
colorlabels-0.7.0.dist-info/METADATA
colorlabels-0.7.0.dist-info/WHEEL
colorlabels-0.7.0.dist-info/top_level.txt
colorlabels-0.7.0.dist-info/RECORD
