Metadata-Version: 2.1
Name: colorlabels
Version: 0.7.0
Summary: Provides colorful and semantic labels in console. Tailored for message display and interaction in automated scripts.
Home-page: https://github.com/gousaiyang/colorlabels
Author: Saiyang Gou
Author-email: gousaiyang223@gmail.com
License: MIT
Keywords: console terminal color message display animation progress progressbar
Platform: UNKNOWN
Classifier: Development Status :: 5 - Production/Stable
Classifier: Environment :: Console
Classifier: Intended Audience :: Developers
Classifier: Intended Audience :: Information Technology
Classifier: Intended Audience :: System Administrators
Classifier: License :: OSI Approved :: MIT License
Classifier: Operating System :: OS Independent
Classifier: Programming Language :: Python :: 2
Classifier: Programming Language :: Python :: 3
Classifier: Topic :: Software Development :: User Interfaces
Classifier: Topic :: Software Development :: Widget Sets
Classifier: Topic :: System :: Logging
Classifier: Topic :: Terminals
Classifier: Topic :: Utilities
Requires-Dist: colorama ; platform_system == "Windows"
